[
  {
    "email": "kush32@gmail.com",
    "password": "popopo"
  },
  {
    "email": "hello@gmail.com",
    "password": "123"
  },
  {
    "email": "abhinav@gmail.com",
    "password": "louda"
  },
  {
    "email": "kavish123@gmail.com",
    "password": "lauda"
  },
  {
    "email": "kushpuri321@gmail.com",
    "password": "popopo"
  },
  {
    "email": "kushpuri399@gmail.com",
    "password": "popopo"
  },
  {
    "email": "kushpuri21@gmail.com",
    "password": "popopo"
  },
  {
    "email": "kushpuri89@gmail.com",
    "password": "popopo"
  },
  {
    "email": "ravi11@gmail.com",
    "password": "popopo"
  },
  {
    "email": "ompande32@gmail.com",
    "password": "popopo"
  }
]